nuva_utils/__init__.py
nuva_utils/nuva_utils.py
nuva_utils-1.1.dist-info/METADATA
nuva_utils-1.1.dist-info/WHEEL
nuva_utils-1.1.dist-info/top_level.txt
nuva_utils-1.1.dist-info/RECORD
