Metadata-Version: 2.4
Name: nuva_utils
Version: 1.1
Summary: Utilities for the Universal Nomenclature of Vaccines (NUVA)
Author: François KAAG
Author-email: François KAAG <francois.kaag@cardynal.fr>
Dynamic: author
